{
	"class" : {
		"newFromICEvent:" : "PS 6/28/2018 14:36",
		"numberToTwoDigitsString:" : "PS 6/7/2018 15:39" },
	"instance" : {
		"<=" : "lh 6/13/2018 17:27",
		"=" : "PS 6/4/2018 15:52",
		"areDatesValid" : "jz 5/30/2018 15:19",
		"autocorrectBegin" : "jz 5/30/2018 16:01",
		"autocorrectEnd" : "jz 5/30/2018 16:01",
		"begin" : "PS 6/7/2018 15:43",
		"begin:" : "PS 5/17/2018 13:14",
		"beginDay" : "PS 5/17/2018 12:02",
		"beginDay:" : "jz 5/30/2018 15:51",
		"beginHour" : "PS 5/17/2018 12:02",
		"beginHour:" : "jz 5/30/2018 15:51",
		"beginMinute" : "PS 5/17/2018 12:03",
		"beginMinute:" : "jz 5/30/2018 15:51",
		"beginMonth" : "PS 5/17/2018 12:02",
		"beginMonth:" : "jz 5/30/2018 15:51",
		"beginYear" : "PS 5/17/2018 12:02",
		"beginYear:" : "jz 5/30/2018 15:51",
		"beginsIn:" : "kk 6/21/2018 16:53",
		"calendar" : "6/4/2018 16:22:48",
		"calendar:" : "6/4/2018 16:22:48",
		"dateAndTimeString" : "PS 6/14/2018 14:27",
		"description" : "PS 5/4/2018 13:42",
		"description:" : "PS 5/4/2018 13:42",
		"end" : "PS 5/22/2018 18:46",
		"end:" : "dm 5/22/2018 18:30",
		"endDay" : "dm 5/22/2018 18:30",
		"endDay:" : "jz 5/30/2018 15:51",
		"endHour" : "dm 5/22/2018 18:31",
		"endHour:" : "jz 5/30/2018 15:51",
		"endMinute" : "dm 5/22/2018 18:31",
		"endMinute:" : "jz 5/30/2018 15:51",
		"endMonth" : "dm 5/22/2018 18:31",
		"endMonth:" : "jz 5/30/2018 15:52",
		"endYear" : "dm 5/22/2018 18:32",
		"endYear:" : "jz 5/30/2018 15:52",
		"endsIn:" : "kk 6/21/2018 16:57",
		"initialize" : "PS 5/17/2018 12:26",
		"isBeginDateValid" : "jz 5/30/2018 15:19",
		"isEndDateValid" : "jz 5/30/2018 15:19",
		"isFullDay" : "kk 6/21/2018 10:30",
		"isFullDayfor:" : "kk 6/21/2018 16:49",
		"isMultipleDay" : "kk 6/21/2018 11:18",
		"isTitleValid" : "jz 6/4/2018 18:27",
		"isValid" : "jz 5/30/2018 15:27",
		"location" : "PS 5/4/2018 13:42",
		"location:" : "PS 5/4/2018 13:42",
		"makeFullDay" : "kk 6/21/2018 10:36",
		"overlaps:" : "lh 6/13/2018 16:31",
		"participants" : "PS 5/4/2018 13:42",
		"participants:" : "PS 5/4/2018 13:42",
		"timeString" : "kk 6/21/2018 11:07",
		"timespan" : "PS 5/4/2018 14:47",
		"title" : "PS 5/4/2018 13:41",
		"title:" : "PS 5/4/2018 13:41" } }
