{
	"class" : {
		"openDay:for:" : "LB 6/30/2021 17:14" },
	"instance" : {
		"app" : "LB 6/30/2021 17:07",
		"app:" : "LB 6/30/2021 17:08",
		"buildDayTextWith:" : "kk 7/5/2018 16:06",
		"buildEventPanelWith:" : "LM 7/12/2021 16:54",
		"buildNextDayButton:" : "kk 7/5/2018 16:07",
		"buildPreviousDayButton:" : "kk 7/5/2018 16:07",
		"buildTimelineWith:" : "kk 7/5/2018 16:07",
		"buildWith:" : "LB 6/30/2021 17:10",
		"buttonHeight" : "kk 6/12/2018 12:26",
		"buttonWidth" : "kk 6/12/2018 12:27",
		"day" : " 8/2/2021 14:44:33",
		"day:" : "kk 6/12/2018 12:28",
		"dayText" : "LM 7/12/2021 16:54",
		"firstDay" : "LM 7/12/2021 16:54",
		"nextDay" : "LM 7/12/2021 16:54",
		"previousDay" : "LM 7/12/2021 16:54",
		"timeLabelWidth" : "lh 6/13/2018 16:42",
		"updateDay" : "LB 6/30/2021 17:12",
		"yPositionFor:and:" : "LB 6/30/2021 17:13" } }
