{
	"class" : {
		 },
	"instance" : {
		"<" : "NMK 6/12/2022 21:16",
		"<=" : "BZ 6/26/2022 12:44",
		"=" : "AN 7/3/2022 14:20",
		">" : "NMK 6/12/2022 21:19",
		">=" : "NMK 6/12/2022 21:20",
		"begin" : "AN 6/7/2022 10:41",
		"begin:" : "AN 6/26/2022 09:26",
		"calendar" : "AN 6/23/2022 11:51",
		"calendar:" : "AN 7/7/2022 16:11",
		"color" : "AN 6/25/2022 22:09",
		"color:" : "AN 6/26/2022 09:26",
		"compressedCopy" : "AN 7/3/2022 12:48",
		"description" : "AN 6/25/2022 23:24",
		"description:" : "AN 6/26/2022 09:26",
		"end" : "AN 6/7/2022 10:41",
		"end:" : "AN 6/26/2022 09:26",
		"hash" : "AN 7/4/2022 20:43",
		"isFullDay" : "AN 7/3/2022 15:17",
		"isInReadOnlyCalendar" : "AN 6/26/2022 08:46",
		"location" : "AN 6/25/2022 23:24",
		"location:" : "AN 6/26/2022 09:26",
		"participants" : "AN 6/25/2022 23:24",
		"participants:" : "AN 6/26/2022 09:27",
		"title" : "AN 7/3/2022 12:49",
		"title:" : "AN 6/26/2022 09:23" } }
