{
	"class" : {
		"createWith:" : "AN 7/14/2022 20:50" },
	"instance" : {
		"areDatesAndTimesValid" : "AN 7/7/2022 11:23",
		"areDatesValid" : "AN 7/7/2022 11:24",
		"begin" : "AN 6/24/2022 10:32",
		"begin:" : "AN 7/3/2022 14:43",
		"beginColor" : "AN 7/8/2022 02:31",
		"beginColor:" : "AN 7/8/2022 02:31",
		"beginDate" : "AN 7/7/2022 11:42",
		"beginDate:" : "AN 7/7/2022 15:32",
		"beginDay" : "AN 6/24/2022 10:02",
		"beginDay:" : "AN 7/7/2022 11:19",
		"beginHour" : "AN 6/24/2022 10:02",
		"beginHour:" : "AN 6/25/2022 13:01",
		"beginMinute" : "AN 6/24/2022 10:03",
		"beginMinute:" : "AN 6/25/2022 13:02",
		"beginMonth" : "AN 6/24/2022 10:03",
		"beginMonth:" : "AN 7/7/2022 11:19",
		"beginYear" : "AN 6/24/2022 10:03",
		"beginYear:" : "AN 7/7/2022 11:19",
		"borderLeft" : "jz 5/10/2018 13:18",
		"borderRight" : "jz 5/10/2018 13:18",
		"buildBeginDayText:" : "AN 7/8/2022 02:32",
		"buildBeginHourText:" : "AN 7/8/2022 02:32",
		"buildBeginMinuteText:" : "AN 7/8/2022 02:32",
		"buildBeginMonthText:" : "AN 7/8/2022 02:32",
		"buildBeginPickerButton:" : "LM 7/12/2021 16:13",
		"buildBeginYearText:" : "AN 7/8/2022 02:32",
		"buildButtons:" : "AN 6/25/2022 21:14",
		"buildCalendarList:" : "AN 7/15/2022 01:08",
		"buildColorPickerButton:" : "AN 6/25/2022 22:01",
		"buildDeleteButton:" : "AN 7/14/2022 21:11",
		"buildDescriptionText:" : "AN 6/24/2022 10:04",
		"buildEditButton:" : "AN 7/8/2022 12:23",
		"buildEndDayText:" : "AN 7/8/2022 02:33",
		"buildEndHourText:" : "AN 7/8/2022 02:33",
		"buildEndMinuteText:" : "AN 7/8/2022 02:33",
		"buildEndMonthText:" : "AN 7/8/2022 02:33",
		"buildEndPickerButton:" : "LM 7/12/2021 16:13",
		"buildEndYearText:" : "AN 7/8/2022 02:32",
		"buildFields:" : "dm 7/24/2018 19:21",
		"buildFullDayButton:" : "AN 7/8/2022 12:18",
		"buildLocationText:" : "AN 7/8/2022 12:19",
		"buildParticipantsText:" : "AN 7/8/2022 12:17",
		"buildSaveButton:" : "AN 7/8/2022 12:16",
		"buildStandardFields:" : "LM 7/12/2021 16:00",
		"buildTitleText:" : "AN 6/24/2022 10:07",
		"buildWith:" : "AN 6/22/2022 17:08",
		"calendar:" : "AN 7/14/2022 20:22",
		"calendarList" : "AN 7/8/2022 12:01",
		"calendarList:" : "AN 7/15/2022 09:59",
		"checkBeginHighlighting" : "AN 7/8/2022 02:45",
		"checkEndHighlighting" : "AN 7/8/2022 02:45",
		"close" : "AN 7/6/2022 18:14",
		"color" : "AN 7/8/2022 12:54",
		"color:" : "AN 6/25/2022 22:40",
		"defaultColor" : "LM 7/12/2021 16:04",
		"defaultColorChange" : "AN 7/8/2022 12:03",
		"defaultEventColor" : "AN 7/14/2022 19:48",
		"defaultHighlightColor" : "AN 7/8/2022 02:38",
		"defaultTextColor" : "NMK 7/10/2022 06:38",
		"description" : "AN 6/24/2022 10:04",
		"description:" : "AN 6/24/2022 10:04",
		"end" : "AN 7/7/2022 11:38",
		"end:" : "AN 7/3/2022 14:44",
		"endColor" : "AN 7/8/2022 02:31",
		"endColor:" : "AN 7/8/2022 02:32",
		"endDate" : "AN 7/7/2022 11:42",
		"endDate:" : "AN 7/7/2022 15:32",
		"endDay" : "AN 6/24/2022 10:05",
		"endDay:" : "AN 7/7/2022 11:19",
		"endHour" : "AN 6/24/2022 10:05",
		"endHour:" : "AN 6/25/2022 13:02",
		"endMinute" : "AN 6/24/2022 10:05",
		"endMinute:" : "AN 6/25/2022 13:02",
		"endMonth" : "AN 6/24/2022 10:05",
		"endMonth:" : "AN 7/7/2022 11:20",
		"endYear" : "AN 6/24/2022 10:06",
		"endYear:" : "AN 7/7/2022 11:20",
		"eventData" : "AN 6/22/2022 11:54",
		"eventData:" : "AN 6/22/2022 11:50",
		"fullDayButtonLabel" : "LM 7/12/2021 16:10",
		"generateEvent" : "AN 6/26/2022 00:03",
		"highlightDatesAndTimes" : "AN 7/8/2022 02:39",
		"highlightErrors" : "AN 7/8/2022 02:06",
		"highlightTitle" : "AN 7/7/2022 18:52",
		"initialize" : "NMK 7/10/2022 06:39",
		"isBeginDateAndTimeValid" : "AN 7/7/2022 11:25",
		"isBeginDateValid" : "AN 7/7/2022 11:25",
		"isEmptyText:" : "AN 6/23/2022 08:30",
		"isEndDateAndTimeValid" : "AN 6/24/2022 10:42",
		"isEndDateValid" : "AN 7/7/2022 11:25",
		"isFullDay" : "AN 7/3/2022 15:20",
		"isFullDaySelected" : "LB 6/21/2021 18:10",
		"isFullDaySelected:" : "LB 5/11/2021 09:53",
		"isReadOnly" : "dm 7/24/2018 19:12",
		"isTitleValid" : "AN 7/3/2022 14:47",
		"isValid" : "AN 7/7/2022 11:23",
		"isValidDay:" : "AN 6/22/2022 16:49",
		"isValidHour:" : "AN 6/22/2022 12:11",
		"isValidMinute:" : "AN 6/23/2022 08:42",
		"isValidMonth:" : "AN 6/22/2022 12:14",
		"isValidYear:" : "AN 6/22/2022 18:50",
		"lineHeight" : "jz 7/25/2018 16:49",
		"lineOffsetOf:" : "LM 7/12/2021 16:13",
		"load:" : "AN 7/15/2022 01:00",
		"location" : "AN 6/24/2022 10:06",
		"location:" : "AN 6/24/2022 10:06",
		"makeFullDay" : "AN 7/3/2022 14:49",
		"participants" : "AN 6/24/2022 10:06",
		"participants:" : "AN 6/24/2022 10:07",
		"pickBeginDate" : "AN 7/7/2022 15:31",
		"pickColor" : "AN 7/8/2022 13:26",
		"pickEndDate" : "AN 7/7/2022 15:31",
		"reloadDates" : "AN 7/7/2022 18:00",
		"spacing" : "jz 7/25/2018 16:48",
		"switchFullDaySelected" : "kk 6/21/2018 10:59",
		"title" : "AN 6/24/2022 10:07",
		"title:" : "AN 7/8/2022 02:17",
		"titleColor" : "AN 7/7/2022 18:51",
		"titleColor:" : "LB 5/11/2021 09:43",
		"titleTextColor" : "kk 7/5/2018 15:29",
		"titleTextColor:" : "LB 5/11/2021 09:47",
		"update:" : "AN 7/15/2022 10:01",
		"updateBegin" : "AN 7/8/2022 02:44",
		"updateBeginDate:" : "AN 7/7/2022 15:32",
		"updateBeginDay:" : "AN 7/7/2022 17:36",
		"updateBeginHour:" : "AN 7/7/2022 17:36",
		"updateBeginMinute:" : "AN 7/7/2022 17:37",
		"updateBeginMonth:" : "AN 7/7/2022 17:37",
		"updateBeginYear:" : "AN 7/7/2022 17:37",
		"updateEnd" : "AN 7/8/2022 02:44",
		"updateEndDate:" : "AN 7/7/2022 15:32",
		"updateEndDay:" : "AN 7/7/2022 17:38",
		"updateEndHour:" : "AN 7/7/2022 17:38",
		"updateEndMinute:" : "AN 7/7/2022 17:38",
		"updateEndMonth:" : "AN 7/7/2022 17:38",
		"updateEndYear:" : "AN 7/7/2022 17:38",
		"windowFields:" : "LM 7/12/2021 16:21",
		"windowTitle" : "kk 7/5/2018 15:30",
		"windows" : "AN 6/25/2022 23:08",
		"windows:" : "AN 6/25/2022 23:08" } }
